setup.cfg
setup.py
metaparticle.egg-info/PKG-INFO
metaparticle.egg-info/SOURCES.txt
metaparticle.egg-info/dependency_links.txt
metaparticle.egg-info/not-zip-safe
metaparticle.egg-info/top_level.txt
metaparticle_pkg/__init__.py
metaparticle_pkg/containerize.py
metaparticle_pkg/docker_builder.py
metaparticle_pkg/docker_runner.py
metaparticle_pkg/metaparticle.py
metaparticle_pkg/metaparticle_runner.py
metaparticle_pkg/option.py
metaparticle_pkg/version.py
metaparticle_pkg/builder/__init__.py
metaparticle_pkg/builder/docker.py
metaparticle_pkg/runner/__init__.py
metaparticle_pkg/runner/docker.py
metaparticle_pkg/runner/metaparticle.py