Metadata-Version: 1.1
Name: metaparticle
Version: 0.4.0
Summary: Easily containerize your python application
Home-page: https://github.com/metaparticle-io/package/tree/master/python
Author: Metaparticle Authors
Author-email: UNKNOWN
License: MIT
Keywords: kubernetes,docker,container,metaparticle
Platform: linux
Classifier: Development Status :: 4 - Beta
Classifier: Environment :: Console
Classifier: Intended Audience :: Developers
Classifier: License :: OSI Approved :: MIT License
Classifier: Natural Language :: English
Classifier: Operating System :: POSIX :: Linux
Classifier: Programming Language :: Python
Classifier: Programming Language :: Python :: 2
Classifier: Programming Language :: Python :: 3
Classifier: Programming Language :: Python :: Implementation :: CPython
Classifier: Topic :: Software Development :: Libraries :: Python Modules
Classifier: Topic :: Utilities
